troyalab/__init__.py
troyalab/RPi_Shield/__init__.py
troyalab-0.1.6.dist-info/METADATA
troyalab-0.1.6.dist-info/WHEEL
troyalab-0.1.6.dist-info/top_level.txt
troyalab-0.1.6.dist-info/RECORD
