Metadata-Version: 2.1
Name: troyalab
Version: 0.1.6
Summary: A library to use for Troyalab development boards for Python
Home-page: https://github.com/troyalab-fatih/BG96_RASPBERY_PI
Author: Fatih Furkan
Author-email: furkan.troyalab@outlook.com
Classifier: Programming Language :: Python :: 3
Classifier: License :: OSI Approved :: MIT License
Classifier: Operating System :: OS Independent
Requires-Python: >=3.9.2
Requires-Dist: pyserial >=3.5b0
Requires-Dist: RPi.GPIO >=0.7.0
